{
  "updated": "2026-03-02T09:00:48.933Z",
  "tz": "America/Los_Angeles",
  "window": {
    "start": "2026-03-02T08:00:00.000Z",
    "days": 14
  },
  "skills": [
    "3D Printing",
    "3D Scanner",
    "CNC Router",
    "Electronics",
    "Fusion 360",
    "Laser Cutting",
    "Laser Cutting Shop Safety",
    "Sewing",
    "Shop Safety",
    "Soldering",
    "Woodworking"
  ],
  "people": [
    {
      "name": "Arnav",
      "location": "Main Room",
      "skills": [
        "3D Printing",
        "Fusion 360",
        "Laser Cutting"
      ],
      "available": [
        {
          "start": "2026-03-04T17:00:00.000Z",
          "end": "2026-03-04T20:00:00.000Z"
        },
        {
          "start": "2026-03-06T17:00:00.000Z",
          "end": "2026-03-06T23:00:00.000Z"
        },
        {
          "start": "2026-03-09T16:00:00.000Z",
          "end": "2026-03-09T22:00:00.000Z"
        },
        {
          "start": "2026-03-11T16:00:00.000Z",
          "end": "2026-03-11T19:00:00.000Z"
        },
        {
          "start": "2026-03-13T16:00:00.000Z",
          "end": "2026-03-13T22:00:00.000Z"
        }
      ]
    },
    {
      "name": "Bryan",
      "location": "Main Room",
      "skills": [
        "3D Printing",
        "Fusion 360",
        "Laser Cutting",
        "3D Scanner"
      ],
      "available": [
        {
          "start": "2026-03-03T17:30:00.000Z",
          "end": "2026-03-04T01:00:00.000Z"
        },
        {
          "start": "2026-03-05T17:30:00.000Z",
          "end": "2026-03-06T01:00:00.000Z"
        },
        {
          "start": "2026-03-10T16:30:00.000Z",
          "end": "2026-03-11T00:00:00.000Z"
        },
        {
          "start": "2026-03-12T16:30:00.000Z",
          "end": "2026-03-13T00:00:00.000Z"
        }
      ]
    },
    {
      "name": "Moses",
      "location": "Main Room",
      "skills": [
        "3D Printing",
        "Laser Cutting"
      ],
      "available": [
        {
          "start": "2026-03-02T20:00:00.000Z",
          "end": "2026-03-03T01:00:00.000Z"
        },
        {
          "start": "2026-03-04T20:00:00.000Z",
          "end": "2026-03-05T01:00:00.000Z"
        },
        {
          "start": "2026-03-09T19:00:00.000Z",
          "end": "2026-03-10T00:00:00.000Z"
        },
        {
          "start": "2026-03-11T19:00:00.000Z",
          "end": "2026-03-12T00:00:00.000Z"
        }
      ]
    },
    {
      "name": "Nathan",
      "location": "",
      "skills": [],
      "available": [
        {
          "start": "2026-03-05T20:30:00.000Z",
          "end": "2026-03-06T01:00:00.000Z"
        },
        {
          "start": "2026-03-12T19:30:00.000Z",
          "end": "2026-03-13T00:00:00.000Z"
        }
      ]
    },
    {
      "name": "Riley",
      "location": "Main Room",
      "skills": [
        "3D Printing",
        "CNC Router",
        "Fusion 360",
        "Laser Cutting",
        "Electronics",
        "Soldering",
        "Woodworking",
        "Sewing",
        "Shop Safety"
      ],
      "available": [
        {
          "start": "2026-03-02T17:00:00.000Z",
          "end": "2026-03-02T21:00:00.000Z"
        },
        {
          "start": "2026-03-03T17:00:00.000Z",
          "end": "2026-03-03T18:00:00.000Z"
        },
        {
          "start": "2026-03-03T19:00:00.000Z",
          "end": "2026-03-04T01:00:00.000Z"
        },
        {
          "start": "2026-03-04T17:00:00.000Z",
          "end": "2026-03-04T23:00:00.000Z"
        },
        {
          "start": "2026-03-05T00:00:00.000Z",
          "end": "2026-03-05T01:00:00.000Z"
        },
        {
          "start": "2026-03-05T17:00:00.000Z",
          "end": "2026-03-05T19:00:00.000Z"
        },
        {
          "start": "2026-03-05T20:00:00.000Z",
          "end": "2026-03-06T01:00:00.000Z"
        },
        {
          "start": "2026-03-06T17:30:00.000Z",
          "end": "2026-03-07T01:00:00.000Z"
        },
        {
          "start": "2026-03-09T16:00:00.000Z",
          "end": "2026-03-09T20:00:00.000Z"
        },
        {
          "start": "2026-03-10T16:00:00.000Z",
          "end": "2026-03-10T16:30:00.000Z"
        },
        {
          "start": "2026-03-10T17:50:00.000Z",
          "end": "2026-03-10T19:00:00.000Z"
        },
        {
          "start": "2026-03-10T20:00:00.000Z",
          "end": "2026-03-11T00:00:00.000Z"
        },
        {
          "start": "2026-03-11T16:00:00.000Z",
          "end": "2026-03-12T00:00:00.000Z"
        },
        {
          "start": "2026-03-12T16:00:00.000Z",
          "end": "2026-03-13T00:00:00.000Z"
        },
        {
          "start": "2026-03-13T16:00:00.000Z",
          "end": "2026-03-14T00:00:00.000Z"
        }
      ]
    },
    {
      "name": "Rita",
      "location": "Main Room",
      "skills": [
        "3D Printing",
        "Laser Cutting Shop Safety"
      ],
      "available": [
        {
          "start": "2026-03-02T17:30:00.000Z",
          "end": "2026-03-02T20:00:00.000Z"
        },
        {
          "start": "2026-03-04T17:30:00.000Z",
          "end": "2026-03-04T20:00:00.000Z"
        },
        {
          "start": "2026-03-09T16:30:00.000Z",
          "end": "2026-03-09T19:00:00.000Z"
        },
        {
          "start": "2026-03-11T16:30:00.000Z",
          "end": "2026-03-11T19:00:00.000Z"
        }
      ]
    },
    {
      "name": "Sofia",
      "location": "",
      "skills": [],
      "available": [
        {
          "start": "2026-03-05T21:00:00.000Z",
          "end": "2026-03-06T00:00:00.000Z"
        },
        {
          "start": "2026-03-06T20:30:00.000Z",
          "end": "2026-03-07T01:00:00.000Z"
        },
        {
          "start": "2026-03-09T19:30:00.000Z",
          "end": "2026-03-10T00:00:00.000Z"
        },
        {
          "start": "2026-03-12T20:00:00.000Z",
          "end": "2026-03-12T23:00:00.000Z"
        },
        {
          "start": "2026-03-13T19:30:00.000Z",
          "end": "2026-03-14T00:00:00.000Z"
        }
      ]
    }
  ]
}